ConglingkaishiDeJsonKuJiaochengFix1/README.md
ConglingkaishiDeJsonKuJiaochengFix1/__init__.py
ConglingkaishiDeJsonKuJiaochengFix1/__main__.py
ConglingkaishiDeJsonKuJiaochengFix1/file.epub
ConglingkaishiDeJsonKuJiaochengFix1/index.html
ConglingkaishiDeJsonKuJiaochengFix1/css/__init__.py
ConglingkaishiDeJsonKuJiaochengFix1/css/annotations.css
ConglingkaishiDeJsonKuJiaochengFix1/css/main.css
ConglingkaishiDeJsonKuJiaochengFix1/css/normalize.css
ConglingkaishiDeJsonKuJiaochengFix1/css/popup.css
ConglingkaishiDeJsonKuJiaochengFix1/font/__init__.py
ConglingkaishiDeJsonKuJiaochengFix1/font/fontello.eot
ConglingkaishiDeJsonKuJiaochengFix1/font/fontello.svg
ConglingkaishiDeJsonKuJiaochengFix1/font/fontello.ttf
ConglingkaishiDeJsonKuJiaochengFix1/font/fontello.woff
ConglingkaishiDeJsonKuJiaochengFix1/img/__init__.py
ConglingkaishiDeJsonKuJiaochengFix1/img/annotator-glyph-sprite.png
ConglingkaishiDeJsonKuJiaochengFix1/img/annotator-icon-sprite.png
ConglingkaishiDeJsonKuJiaochengFix1/img/apple-touch-icon.png
ConglingkaishiDeJsonKuJiaochengFix1/img/cancelfullscreen.png
ConglingkaishiDeJsonKuJiaochengFix1/img/close.png
ConglingkaishiDeJsonKuJiaochengFix1/img/fullscreen.png
ConglingkaishiDeJsonKuJiaochengFix1/img/loader.gif
ConglingkaishiDeJsonKuJiaochengFix1/img/menu-icon.png
ConglingkaishiDeJsonKuJiaochengFix1/img/save.png
ConglingkaishiDeJsonKuJiaochengFix1/img/saved.png
ConglingkaishiDeJsonKuJiaochengFix1/img/settings-s.png
ConglingkaishiDeJsonKuJiaochengFix1/img/settings.png
ConglingkaishiDeJsonKuJiaochengFix1/img/star.png
ConglingkaishiDeJsonKuJiaochengFix1/js/__init__.py
ConglingkaishiDeJsonKuJiaochengFix1/js/epub.js
ConglingkaishiDeJsonKuJiaochengFix1/js/epub.min.js
ConglingkaishiDeJsonKuJiaochengFix1/js/epub.min.map
ConglingkaishiDeJsonKuJiaochengFix1/js/hooks.min.js
ConglingkaishiDeJsonKuJiaochengFix1/js/hooks.min.map
ConglingkaishiDeJsonKuJiaochengFix1/js/reader.js
ConglingkaishiDeJsonKuJiaochengFix1/js/reader.js.map
ConglingkaishiDeJsonKuJiaochengFix1/js/reader.min.js
conglingkaishi_de_json_ku_jiaocheng_fix1-2025.3.25.1.dist-info/METADATA
conglingkaishi_de_json_ku_jiaocheng_fix1-2025.3.25.1.dist-info/WHEEL
conglingkaishi_de_json_ku_jiaocheng_fix1-2025.3.25.1.dist-info/entry_points.txt
conglingkaishi_de_json_ku_jiaocheng_fix1-2025.3.25.1.dist-info/top_level.txt
conglingkaishi_de_json_ku_jiaocheng_fix1-2025.3.25.1.dist-info/RECORD
